jupyterlab_k8s_explorer/__init__.py
jupyterlab_k8s_explorer/_version.py
jupyterlab_k8s_explorer/handlers.py
jupyterlab_k8s_explorer/k8s.py
jupyterlab_k8s_explorer/k8s_handler.py
jupyterlab_k8s_explorer/labextension/build_log.json
jupyterlab_k8s_explorer/labextension/package.json
jupyterlab_k8s_explorer/labextension/schemas/jupyterlab_k8s_explorer/package.json.orig
jupyterlab_k8s_explorer/labextension/schemas/jupyterlab_k8s_explorer/plugin.json
jupyterlab_k8s_explorer/labextension/static/lib_index_js-webpack_sharing_consume_default_react-dom.94520f5fefed57b3f556.js
jupyterlab_k8s_explorer/labextension/static/lib_index_js-webpack_sharing_consume_default_react-dom.94520f5fefed57b3f556.js.map
jupyterlab_k8s_explorer/labextension/static/node_modules_uiw_codemirror-theme-sublime_esm_index_js-_d6210.390d5f6ea8e0549f82e1.js
jupyterlab_k8s_explorer/labextension/static/node_modules_uiw_codemirror-theme-sublime_esm_index_js-_d6210.390d5f6ea8e0549f82e1.js.map
jupyterlab_k8s_explorer/labextension/static/node_modules_uiw_codemirror-theme-sublime_esm_index_js-_d6211.8d1cc12d597691a9e32f.js
jupyterlab_k8s_explorer/labextension/static/node_modules_uiw_codemirror-theme-sublime_esm_index_js-_d6211.8d1cc12d597691a9e32f.js.map
jupyterlab_k8s_explorer/labextension/static/remoteEntry.dc27590ffb5bed3ff814.js
jupyterlab_k8s_explorer/labextension/static/remoteEntry.dc27590ffb5bed3ff814.js.map
jupyterlab_k8s_explorer/labextension/static/style.js
jupyterlab_k8s_explorer/labextension/static/style_index_js.b1ae900efbcb7a7efaea.js
jupyterlab_k8s_explorer/labextension/static/style_index_js.b1ae900efbcb7a7efaea.js.map
jupyterlab_k8s_explorer/labextension/static/vendors-node_modules_bootstrap_dist_css_bootstrap_min_css.5c4f248916a068b3956e.js
jupyterlab_k8s_explorer/labextension/static/vendors-node_modules_bootstrap_dist_css_bootstrap_min_css.5c4f248916a068b3956e.js.map
jupyterlab_k8s_explorer/labextension/static/vendors-node_modules_codemirror_language_dist_index_js.262ca10885a944719679.js
jupyterlab_k8s_explorer-0.1.0.dist-info/LICENSE
jupyterlab_k8s_explorer-0.1.0.dist-info/METADATA
jupyterlab_k8s_explorer-0.1.0.dist-info/WHEEL
jupyterlab_k8s_explorer-0.1.0.dist-info/top_level.txt
jupyterlab_k8s_explorer-0.1.0.dist-info/RECORD
